piyathon/__init__.py
piyathon/keywords.py
piyathon/p2p.py
piyathon/piyathon.py
piyathon/piyathon_translator.py
piyathon/Lib/สุ่ม.py
piyathon/Lib/เต่า.py
piyathon-0.3.12.11.dist-info/METADATA
piyathon-0.3.12.11.dist-info/WHEEL
piyathon-0.3.12.11.dist-info/entry_points.txt
piyathon-0.3.12.11.dist-info/licenses/LICENSE
piyathon-0.3.12.11.dist-info/RECORD
