Metadata-Version: 2.3
Name: piyathon
Version: 0.3.12.11
Summary: A Thai language-localized superset of Python with a bi-directional transformer to standard Python
Project-URL: Homepage, https://github.com/piyawish/piyathon
Project-URL: Bug Tracker, https://github.com/piyawish/piyathon/issues
Author-email: Piyawish Piyawat <contact@piyawatana.com>
License: MIT
License-File: LICENSE
Classifier: License :: OSI Approved :: MIT License
Classifier: Operating System :: OS Independent
Classifier: Programming Language :: Python :: 3.12
Requires-Python: >=3.12
